{
	"identifier": "Level_2",
	"uniqueIdentifer": "5ba61f90-5e50-11f0-870b-6d1cb22524df",
	"x": -1,
	"y": -1,
	"width": 512,
	"height": 288,
	"bgColor": "#696A79",
	"neighbourLevels": [],
	"customFields": {
		"maximumPlayerPasts": 1
	},
	"layers": [
		"Background.png",
		"Terrain.png",
		"Decoration.png"
	],
	"entities": {
		"Finish": [
			{
				"id": "Finish",
				"iid": "5ba646a0-5e50-11f0-870b-a7595f8a7e76",
				"layer": "Entities",
				"x": 320,
				"y": 176,
				"width": 16,
				"height": 16,
				"color": 6539085,
				"customFields" : {}
			}
		],
		"Start": [
			{
				"id": "Start",
				"iid": "5ba646a1-5e50-11f0-870b-b7b46c29a1c2",
				"layer": "Entities",
				"x": 128,
				"y": 240,
				"width": 16,
				"height": 16,
				"color": 11882632,
				"customFields" : {}
			}
		]
	}
}